velopix-0.9.0.dist-info/METADATA
velopix-0.9.0.dist-info/WHEEL
velopix-0.9.0.dist-info/licenses/LICENSE
velopix/DetectorEvent/__init__.py
velopix/DetectorEvent/__init__.pyi
velopix/DetectorEvent/__pycache__/__init__.cpython-313.pyc
velopix/ReconstructionAlgorithms/__init__.py
velopix/ReconstructionAlgorithms/__init__.pyi
velopix/ReconstructionAlgorithms/__pycache__/__init__.cpython-313.pyc
velopix/Validator/__init__.py
velopix/Validator/__init__.pyi
velopix/Validator/__pycache__/__init__.cpython-313.pyc
velopix/__init__.py
velopix/__init__.pyi
velopix/__pycache__/__init__.cpython-313.pyc
velopix/hyperParameterFramework/__init__.py
velopix/hyperParameterFramework/__pycache__/__init__.cpython-313.pyc
velopix/hyperParameterFramework/__pycache__/event_metrics.cpython-313.pyc
velopix/hyperParameterFramework/__pycache__/optimizers.cpython-313.pyc
velopix/hyperParameterFramework/__pycache__/pipeline.cpython-313.pyc
velopix/hyperParameterFramework/__pycache__/reconstruction_algorithms.cpython-313.pyc
velopix/hyperParameterFramework/__pycache__/velopixTypes.cpython-313.pyc
velopix/hyperParameterFramework/_event_metrics.py
velopix/hyperParameterFramework/_optimizers.py
velopix/hyperParameterFramework/_pipeline.py
velopix/hyperParameterFramework/_reconstruction_algorithms.py
velopix/hyperParameterFramework/_velopixTypes.py
velopix/hyperParameterFramework/solvers/_Bayesian.py
velopix/hyperParameterFramework/solvers/_GridSearch.py
velopix/hyperParameterFramework/solvers/_ParticleSwarm.py
velopix/hyperParameterFramework/solvers/_PolyHoot.py
velopix/hyperParameterFramework/solvers/__init__.py
velopix/hyperParameterFramework/solvers/__pycache__/Bayesian.cpython-313.pyc
velopix/hyperParameterFramework/solvers/__pycache__/GridSearch.cpython-313.pyc
velopix/hyperParameterFramework/solvers/__pycache__/ParticleSwarm.cpython-313.pyc
velopix/hyperParameterFramework/solvers/__pycache__/__init__.cpython-313.pyc
velopix/py.typed
velopix/velopix.cp39-win_amd64.pyd
velopix-0.9.0.dist-info/RECORD
